cases/__init__.py
cases/test_main.py
utils/__init__.py
utils/allure_util.py
utils/assert_util.py
utils/basic_util.py
utils/file_util.py
utils/http_util.py
utils/pg_server_util.py
utils/playwright_util.py
utils/sql_server_util.py
feifei_pytest-1.0.2.dist-info/LICENSE
feifei_pytest-1.0.2.dist-info/METADATA
feifei_pytest-1.0.2.dist-info/WHEEL
feifei_pytest-1.0.2.dist-info/top_level.txt
feifei_pytest-1.0.2.dist-info/RECORD
